LICENSE
README.md
pyproject.toml
setup.py
pyxxljob/__init__.py
pyxxljob/ctx.py
pyxxljob/enum.py
pyxxljob/error.py
pyxxljob/executor.py
pyxxljob/main.py
pyxxljob/schema.py
pyxxljob/server.py
pyxxljob/setting.py
pyxxljob/types.py
pyxxljob/utils.py
pyxxljob/xxl_client.py
pyxxljob.egg-info/PKG-INFO
pyxxljob.egg-info/SOURCES.txt
pyxxljob.egg-info/dependency_links.txt
pyxxljob.egg-info/top_level.txt
pyxxljob.egg-info/zip-safe